nmpyy/__init__.py
nmpyy/a10a.py
nmpyy/a1a.py
nmpyy/a1b.py
nmpyy/a2a.py
nmpyy/a3a.py
nmpyy/a4a.py
nmpyy/a5a.py
nmpyy/a6a.py
nmpyy/a7a.py
nmpyy/a8a.py
nmpyy/a9a.py
nmpyy-0.1.0.dist-info/METADATA
nmpyy-0.1.0.dist-info/WHEEL
nmpyy-0.1.0.dist-info/top_level.txt
nmpyy-0.1.0.dist-info/RECORD
